CHANGES.txt
LICENSE.txt
MANIFEST.in
README.txt
setup.py
bin/randomiser.py
wallpyper/__init__.py
wallpyper/wp.py
wallpyper.egg-info/PKG-INFO
wallpyper.egg-info/SOURCES.txt
wallpyper.egg-info/dependency_links.txt
wallpyper.egg-info/top_level.txt