Metadata-Version: 1.0
Name: wallpyper
Version: 0.0.2
Summary: Tiny Python module handling Linux wallpaper changes
Home-page: https://github.com/unwitting/wallpyper
Author: https://github.com/unwitting
Author-email: jackprestonuk@gmail.com
License: LICENSE.txt
Platform: UNKNOWN
